higher/__init__.py
higher/optim.py
higher/patch.py
higher/utils.py
higher-0.2.1.dist-info/LICENSE
higher-0.2.1.dist-info/METADATA
higher-0.2.1.dist-info/WHEEL
higher-0.2.1.dist-info/top_level.txt
higher-0.2.1.dist-info/RECORD
