Metadata-Version: 2.1
Name: higher
Version: 0.2.1
Summary: A pytorch library allowing users to obtain higher order gradients over losses spanning training loops rather than individual training steps.
Home-page: https://github.com/facebookresearch/higher
Author: Edward Grefenstette
Author-email: egrefen@fb.com
License: Apache
Keywords: second-order,gradient descent,optimization,meta-learning
Platform: UNKNOWN
Classifier: License :: OSI Approved :: Apache Software License
Classifier: Programming Language :: Python
Classifier: Programming Language :: Python :: 3
Classifier: Programming Language :: Python :: 3.6
Requires-Python: >=3.6.0
Requires-Dist: torch
